Workbook
Name Aporte: 'Página1'!$C$13
Name Patrimônio: 'Página1'!$C$16
Name Rendimento_Carteira: 'Página1'!$F$14
Name Tx_mensal: 'Página1'!$C$15
Name Qtd_Anos: 'Página1'!$C$14

Sheet Página1
B12: INVESTIMENTO MENSAL | E12: CONFIGURAÇÕES
B13: Quanto investir por mês ? | C13: 200 | E13: Salário | F13: 5000
B14: Por Quantos Anos ? | C14: 5 | E14: Rendimento Carteira | F14: 0.0089
B15: Taxa de Rendimento mensal ? | C15: 0.01079 | E15: Sugestão de Investimento | F15: =F13*30% -> 1500
B16: Patrimônio acumulado ? | C16: =FV(C15,C14*12,C13*-1) -> 16755.383
B17: Dividendos Mensais ? | C17: =Patrimônio*$F$14 -> 149.12291
A19: 2 | B19: Cenários | D19: Dividendo
A20: 5 | B20: Quanto em 2 anos ? | C20: =FV($C$15,$A19*12,$C$13*-1) -> 5445.5255 | D20: =(C20*$F$14) -> 48.465177
A21: 10 | B21: Quanto em 5 anos ? | C21: =FV($C$15,$A20*12,$C$13*-1) -> 16755.383 | D21: =(C21*$F$14) -> 149.12291
A22: 20 | B22: Quanto em 10 anos ? | C22: =FV($C$15,$A21*12,$C$13*-1) -> 48656.843 | D22: =(C22*$F$14) -> 433.0459
A23: 30 | B23: Quanto em 20 anos ? | C23: =FV($C$15,$A22*12,$C$13*-1) -> 225039.68 | D23: =(C23*$F$14) -> 2002.8532
B24: Quanto em 30 anos ? | C24: =FV($C$15,$A23*12,$C$13*-1) -> 864433.93 | D24: =(C24*$F$14) -> 7693.462
B26: PERFIL | C26: Agressivo
B27: Valor a ser inverstido por mês | C27: =C13 -> 200
B29: Tipo de FII | C29: Percentual sugerido | D29: Valores
B30: PAPEL | C30: =VLOOKUP($C$26&"-"&B30,'Página2'!$A:$D,4,false) -> 0.5 | D30: =(C30*$C$27) -> 100
B31: TIJOLO | C31: =VLOOKUP($C$26&"-"&B31,'Página2'!$A:$D,4,false) -> 0.1 | D31: =(C31*$C$27) -> 20
B32: HÍBRIDOS | C32: =VLOOKUP($C$26&"-"&$B$32,'Página2'!$A:$D,4,false) -> 0.05 | D32: =(C32*$C$27) -> 10
B33: FOFs | C33: =VLOOKUP($C$26&"-"&$B$33,'Página2'!$A:$D,4,false) -> 0.05 | D33: =(C33*$C$27) -> 10
B34: DESENVOLVIMENTO | C34: =VLOOKUP($C$26&"-"&$B$34,'Página2'!$A:$D,4,false) -> 0.2 | D34: =(C34*$C$27) -> 40
B35: HOTELARIAS | C35: =VLOOKUP($C$26&"-"&$B$35,'Página2'!$A:$D,4,false) -> 0.1 | D35: =(C35*$C$27) -> 20
B36: TOTAL | D36: =SUM(D30:D35) -> 200

Sheet Página2
A3: CHAVE | B3: PERFIL | C3: Tipo de FII | D3: % | G3: %
A4: =B4&"-"&C4 -> Conservador-PAPEL | B4: Conservador | C4: PAPEL | D4: 0.3
A5: =B5&"-"&C5 -> Conservador-TIJOLO | B5: Conservador | C5: TIJOLO | D5: 0.5 | F5: =B11&"-"&C11 -> Moderado-TIJOLO | G5: =VLOOKUP(A11,$A:$D,4,FALSE()) -> 0.35
A6: =B6&"-"&C6 -> Conservador-HÍBRIDOS | B6: Conservador | C6: HÍBRIDOS | D6: 0.1
A7: =B7&"-"&C7 -> Conservador-FOFs | B7: Conservador | C7: FOFs | D7: 0.1
A8: =B8&"-"&C8 -> Conservador-DESENVOLVIMENTO | B8: Conservador | C8: DESENVOLVIMENTO | D8: 0
A9: =B9&"-"&C9 -> Conservador-HOTELARIAS | B9: Conservador | C9: HOTELARIAS | D9: 0
A10: =B10&"-"&C10 -> Moderado-PAPEL | B10: Moderado | C10: PAPEL | D10: 0.32
A11: =B11&"-"&C11 -> Moderado-TIJOLO | B11: Moderado | C11: TIJOLO | D11: 0.35
A12: =B12&"-"&C12 -> Moderado-HÍBRIDOS | B12: Moderado | C12: HÍBRIDOS | D12: 0.08
A13: =B13&"-"&C13 -> Moderado-FOFs | B13: Moderado | C13: FOFs | D13: 0.05
A14: =B14&"-"&C14 -> Moderado-DESENVOLVIMENTO | B14: Moderado | C14: DESENVOLVIMENTO | D14: 0.1
A15: =B15&"-"&C15 -> Moderado-HOTELARIAS | B15: Moderado | C15: HOTELARIAS | D15: 0.1
A16: =B16&"-"&C16 -> Agressivo-PAPEL | B16: Agressivo | C16: PAPEL | D16: 0.5
A17: =B17&"-"&C17 -> Agressivo-TIJOLO | B17: Agressivo | C17: TIJOLO | D17: 0.1
... A21: =B21&"-"&C21 -> Agressivo-HOTELARIAS | B21: Agressivo | C21: HOTELARIAS | D21: 0.1
